pybomwater/__init__.py
pybomwater/_version.py
pybomwater/bom_water.py
pybomwater/cache/stations.json
pybomwater/cache/waterML_GetDataAvailability.json
pybomwater/spatial_util.py
pybomwater-0.1.3.dist-info/LICENSE
pybomwater-0.1.3.dist-info/METADATA
pybomwater-0.1.3.dist-info/WHEEL
pybomwater-0.1.3.dist-info/RECORD
