Metadata-Version: 2.1
Name: pybomwater
Version: 0.1.3
Summary: A python tool for requesting data from BoM Sensor Observation Service (SOS2, as WaterML 2.0 format)
License: CSIRO Open Source Software Licence Agreement (variation of the BSD / MIT License)
Author: Andrew Freebairn
Author-email: andrew.freebairn@csiro.au
Requires-Python: >=3.10,<4.0
Classifier: License :: Other/Proprietary License
Classifier: Programming Language :: Python :: 3
Classifier: Programming Language :: Python :: 3.10
Classifier: Programming Language :: Python :: 3.11
Classifier: Programming Language :: Python :: 3.12
Requires-Dist: codecov (>=2.1.13,<3.0.0)
Requires-Dist: fiona (==1.10b2)
Requires-Dist: geojson (>=3.0.1,<4.0.0)
Requires-Dist: geopandas (>=0.14.0,<0.15.0)
Requires-Dist: iso8601 (>=2.1.0,<3.0.0)
Requires-Dist: lxml (>=4.9.3,<5.0.0)
Requires-Dist: netcdf4 (>=1.6.4,<2.0.0)
Requires-Dist: owslib (>=0.29.2,<0.30.0)
Requires-Dist: pandas (>=2.1.1,<3.0.0)
Requires-Dist: pytest (>=7.4.2,<8.0.0)
Requires-Dist: pytest-cov (>=4.1.0,<5.0.0)
Requires-Dist: pytest-github-actions-annotate-failures (>=0.2.0,<0.3.0)
Requires-Dist: pytz (>=2023.3.post1,<2024.0)
Requires-Dist: requests (>=2.31.0,<3.0.0)
Requires-Dist: scipy (>=1.11.3,<2.0.0)
Requires-Dist: setuptools (>=70.0.0,<71.0.0)
Requires-Dist: shapely (>=2.0.1,<3.0.0)
Requires-Dist: wheel (>=0.41.2,<0.42.0)
Requires-Dist: xarray (>=2023.9.0,<2024.0.0)
Requires-Dist: xmltodict (>=0.13.0,<0.14.0)
